{
  "WindowsFeatures": [
    "Web-Server",
    "Web-Mgmt-Console"
  ],
  "Installers": [
    {
      "Name": "ArcGIS for Server",
      "SourcePath": "C:\\Setups\\ArcGISforServer.exe",
      "RemotePath": "ArcGISforServer.exe",
      "LocalPath": "$env:SystemDrive\\ArcGIS\\Deployment\\Downloads\\Server",
      "Arguments": "/qn INSTALLDIR=\"$env:SystemDrive\\ArcGIS\\Server\" INSTALLDIR1=$env:SystemDrive\\Python27 ACCEPTEULA=YES",
      "IsMsi": false,
      "ProductId": "4130E39E-FD8C-4DE0-AE91-AFEC71063B2D",
      "Version": "11.2",
      "Patches": [],
      "AdditionalFiles": []
    },
    {
      "Name": "Portal for ArcGIS",
      "SourcePath": "C:\\Setups\\PortalforArcGIS.exe",
      "RemotePath": "PortalforArcGIS.exe",
      "LocalPath": "$env:SystemDrive\\ArcGIS\\Deployment\\Downloads\\Portal",
      "Arguments": "/qb INSTALLDIR=\"$env:SystemDrive\\ArcGIS\\Portal\" CONTENTDIR=$env:SystemDrive\\portalforarcgis\\content ACCEPTEULA=YES",
      "IsMsi": false,
      "ProductId": "F03C23C1-1F2C-42D0-85C4-38F49B710035",
      "Version": "11.2",
      "Patches": [],
      "AdditionalFiles": []
    },
    {
      "Name": "Web Styles",
      "SourcePath": "C:\\Setups\\WebStyles.exe",
      "RemotePath": "WebStyles.exe",
      "LocalPath": "$env:SystemDrive\\ArcGIS\\Deployment\\Downloads\\WebStyles",
      "Arguments": "/qb ",
      "IsMsi": false,
      "ProductId": "0508DE8B-B6B2-42AD-B955-77451C3ACB60",
      "Version": "11.2",
      "Patches": [],
      "AdditionalFiles": []
    },
    {
      "Name": "DataStore",
      "SourcePath": "C:\\Setups\\DataStore.exe",
      "RemotePath": "DataStore.exe",
      "LocalPath": "$env:SystemDrive\\ArcGIS\\Deployment\\Downloads\\DataStore",
      "Arguments": "/qb INSTALLDIR=\"$env:SystemDrive\\ArcGIS\\DataStore\" ACCEPTEULA=YES ADDLOCAL=ALL",
      "IsMsi": false,
      "ProductId": "FE7F4A14-4D96-4B31-8937-BA19C0A92DDB",
      "Version": "11.2",
      "Patches": [],
      "AdditionalFiles": []
    },
    {
      "Name": "GeoEvent",
      "SourcePath": "C:\\Setups\\GeoEvent.exe",
      "RemotePath": "GeoEvent.exe",
      "LocalPath": "$env:SystemDrive\\ArcGIS\\Deployment\\Downloads\\GeoEvent",
      "Arguments": "/qb ACCEPTEULA=YES",
      "IsMsi": false,
      "ProductId": "7CBB01F9-90D3-42A6-99A8-70E773B5E8C5",
      "Version": "11.2",
      "Patches": [],
      "AdditionalFiles": []
    },
    {
      "Name": "Notebook Server",
      "SourcePath": "C:\\Setups\\NotebookServer.exe",
      "RemotePath": "NotebookServer.exe",
      "LocalPath": "$env:SystemDrive\\ArcGIS\\Deployment\\Downloads\\NotebookServer",
      "Arguments": "/qb INSTALLDIR=\"$env:SystemDrive\\ArcGIS\\NotebookServer\" ACCEPTEULA=YES",
      "IsMsi": false,
      "ProductId": "7CF68441-8657-48C3-93C2-DB2DC3EFA9E5",
      "Version": "11.2",
      "Patches": [],
      "AdditionalFiles": []
    },
    {
      "Name": "Notebook Server Samples Data",
      "SourcePath": "C:\\Setups\\NotebookServerSamplesData.exe",
      "RemotePath": "NotebookServerSamplesData.exe",
      "LocalPath": "$env:SystemDrive\\ArcGIS\\Deployment\\Downloads\\NotebookServerSamplesData",
      "Arguments": "/qb ACCEPTEULA=YES",
      "IsMsi": false,
      "ProductId": "3A9E12F6-7D4B-4DA2-BA2C-C9D0E900CF94",
      "Version": "11.2",
      "Patches": [],
      "AdditionalFiles": []
    },
    {
      "Name": "Mission Server",
      "SourcePath": "C:\\Setups\\MissionServer.exe",
      "RemotePath": "MissionServer.exe",
      "LocalPath": "$env:SystemDrive\\ArcGIS\\Deployment\\Downloads\\MissionServer",
      "Arguments": "/qb INSTALLDIR=\"$env:SystemDrive\\ArcGIS\\Mission\" ACCEPTEULA=YES",
      "IsMsi": false,
      "ProductId": "5721BCA3-D4BB-42D3-A719-787D0B11F478",
      "Version": "11.2",
      "Patches": [],
      "AdditionalFiles": []
    },
    {
      "Name": "Workflow Manager Server",
      "SourcePath": "C:\\Setups\\WorkflowManagerServer.exe",
      "RemotePath": "WorkflowManagerServer.exe",
      "LocalPath": "$env:SystemDrive\\ArcGIS\\Deployment\\Downloads\\WorkflowManagerServer",
      "Arguments": "/qb ACCEPTEULA=YES",
      "IsMsi": false,
      "ProductId": "434D85E9-9CFB-4683-9FFF-5C38CDEBD676",
      "Version": "11.2",
      "Patches": [],
      "AdditionalFiles": []
    },
    {
      "Name": "Web Adaptor IIS",
      "SourcePath": "C:\\Setups\\WebAdaptorIIS.exe",
      "RemotePath": "WebAdaptorIIS.exe",
      "LocalPath": "$env:SystemDrive\\ArcGIS\\Deployment\\Downloads\\WebAdaptorIIS",
      "Arguments": "",
      "SkipInstall": true,
      "IsMsi": false,
      "ProductId": "",
      "Version": "11.2",
      "Patches": [],
      "AdditionalFiles": [
        "C:\\Setups\\dotnet-hosting-6.0.24-win.exe",
        "C:\\Setups\\WebDeploy_amd64_en-US.msi"
      ]
    },
    {
      "Name": "Microsoft ODBC Driver 17 for SQL Server",
      "SourcePath": "C:\\Setups\\msodbcsql_17.10.5_x64.msi",
      "RemotePath": "msodbcsql_17.10.5_x64.msi",
      "LocalPath": "$env:SystemDrive\\ArcGIS\\Deployment\\Downloads\\SQLNativeClient",
      "Arguments": "/quiet /qn IACCEPTMSODBCSQLLICENSETERMS=YES ADDLOCAL=ALL",
      "IsMsi": true,
      "ProductId": "57B9F896-DE52-4CFA-B7DE-9EFD00A1E020"
    },
    {
      "Name": "Microsoft ODBC Driver 18 for SQL Server",
      "SourcePath": "C:\\Setups\\msodbcsql_18.3.2.1_x64.msi",
      "RemotePath": "msodbcsql_18.3.2.1_x64.msi",
      "LocalPath": "$env:SystemDrive\\ArcGIS\\Deployment\\Downloads\\SQLNativeClient",
      "Arguments": "/quiet /qn IACCEPTMSODBCSQLLICENSETERMS=YES ADDLOCAL=ALL",
      "IsMsi": true,
      "ProductId": "4250BFD2-7B44-4EE5-9595-3A448829B329"
    },
    {
      "Name": "Microsoft SQL Command Line Utility 15.0.4298.1",
      "SourcePath": "C:\\Setups\\MsSqlCmdLnUtils_15.0.4298.1.msi",
      "RemotePath": "MsSqlCmdLnUtils_15.0.4298.1.msi",
      "LocalPath": "$env:SystemDrive\\ArcGIS\\Deployment\\Downloads\\SQLNativeClient",
      "Arguments": "/quiet /qn IACCEPTMSSQLCMDLNUTILSLICENSETERMS=YES",
      "IsMsi": true,
      "ProductId": "6F11B2D6-193B-4216-A8E6-D7092834F8FB"
    }
  ]
}